adafruit_testrepo.py
adafruit_circuitpython_testrepo-3.2.2.dist-info/LICENSE
adafruit_circuitpython_testrepo-3.2.2.dist-info/METADATA
adafruit_circuitpython_testrepo-3.2.2.dist-info/WHEEL
adafruit_circuitpython_testrepo-3.2.2.dist-info/top_level.txt
adafruit_circuitpython_testrepo-3.2.2.dist-info/RECORD
