Metadata-Version: 2.1
Name: adafruit-circuitpython-testrepo
Version: 3.2.2
Summary: CircuitPython test library
Author-email: Adafruit Industries <circuitpython@adafruit.com>
License: MIT
Project-URL: Homepage, https://github.com/adafruit/Adafruit_CircuitPython_TestRepo
Keywords: adafruit,blinka,circuitpython,micropython,test
Classifier: Intended Audience :: Developers
Classifier: Topic :: Software Development :: Libraries
Classifier: Topic :: Software Development :: Embedded Systems
Classifier: Topic :: System :: Hardware
Classifier: License :: OSI Approved :: MIT License
Classifier: Programming Language :: Python :: 3
License-File: LICENSE
Requires-Dist: Adafruit-Blinka
Requires-Dist: hidapi
Provides-Extra: optional
